jsonio/__init__.py
jsonio/main.py
ayrun_jsonio-0.1.0.dist-info/LICENSE
ayrun_jsonio-0.1.0.dist-info/METADATA
ayrun_jsonio-0.1.0.dist-info/WHEEL
ayrun_jsonio-0.1.0.dist-info/RECORD
