Metadata-Version: 2.1
Name: ayrun-jsonio
Version: 0.1.0
Summary: 🚀 Seamless JSON handling in Python 🐍
Author: itzAyrun
Author-email: ayrun3412@gmail.com
Requires-Python: >=3.12,<4.0
Classifier: Programming Language :: Python :: 3
Classifier: Programming Language :: Python :: 3.12
Requires-Dist: orjson (>=3.10.7,<4.0.0)
